{
    "attributes": [
        {
            "description": "Overlay archetypes, i.e. partial archetypes that include full definition and terminology, but logically derive all their meta-data from the owning template.",
            "multiplicity": "0..1",
            "name": "overlays",
            "type": "List"
        }
    ],
    "constants": [],
    "functions": [],
    "meta_info": {
        "base_types": [
            "AUTHORED_ARCHETYPE"
        ],
        "classifier": "Class",
        "description": "Class representing source template, i.e. a kind of archetype that may include template overlays, and may be restricted by tools to only defining mandations, prohibitions, and restrictions on elements already defined in the flat parent.",
        "name": "TEMPLATE"
    }
}